{
  "binary_name": "wepp_260513",
  "binary_role": "watershed",
  "built_utc": "2026-05-13T23:01:29Z",
  "features": {
    "hbp_pass_family": "H*.hbp",
    "hbp_schema_major": 1,
    "hbp_schema_minor": 0,
    "hbp_supported": true,
    "legacy_ascii_pass_family": "H*.pass.dat",
    "mode2_direct_hbp_reader": true,
    "mode2_master_pass_prompt_required": false,
    "mode3_process_pass_reload": false,
    "process_mode_pass_pw0_required": false
  },
  "release_tag": "260513-ebepeak-fix",
  "schema": "wepp-binary-release-metadata-v1",
  "sha256": "2670aea4b8960495638ed2eac7999c49478d0e38e74ed1516eb4adf76c498419",
  "source_commit": "32a2290c3cfcc3709bd1329d4590fc353c49b558",
  "source_repo": "wepp-in-the-woods/wepp-forest",
  "validation": {
    "host_smoke": "not_run",
    "lane_quarantine": [
      "reconciled-condenser",
      "chinless-half-hour"
    ],
    "ps05_reader": "not_run",
    "ps06_lane": "geodetic-innocence"
  },
  "wepp_banner_version": "unknown"
}
